[
    {
        "c": 65,
        "d": 1764288000,
        "e": 849,
        "o": 541,
        "p": 1,
        "r": 503,
        "w": 0
    },
    {
        "c": 65,
        "d": 1763683200,
        "e": 849,
        "o": 540,
        "p": 1,
        "r": 504,
        "w": 0
    },
    {
        "c": 65,
        "d": 1763078400,
        "e": 848,
        "o": 536,
        "p": 1,
        "r": 505,
        "w": 0
    },
    {
        "c": 65,
        "d": 1762473600,
        "e": 847,
        "o": 534,
        "p": 1,
        "r": 505,
        "w": 0
    },
    {
        "c": 65,
        "d": 1761868800,
        "e": 847,
        "o": 533,
        "p": 1,
        "r": 506,
        "w": 0
    },
    {
        "c": 65,
        "d": 1761264000,
        "e": 846,
        "o": 532,
        "p": 1,
        "r": 506,
        "w": 0
    },
    {
        "c": 64,
        "d": 1760659200,
        "e": 846,
        "o": 528,
        "p": 1,
        "r": 507,
        "w": 0
    },
    {
        "c": 64,
        "d": 1760054400,
        "e": 845,
        "o": 528,
        "p": 1,
        "r": 508,
        "w": 0
    },
    {
        "c": 64,
        "d": 1759449600,
        "e": 845,
        "o": 527,
        "p": 1,
        "r": 508,
        "w": 0
    },
    {
        "c": 64,
        "d": 1758844800,
        "e": 844,
        "o": 526,
        "p": 1,
        "r": 509,
        "w": 0
    },
    {
        "c": 64,
        "d": 1758240000,
        "e": 843,
        "o": 520,
        "p": 1,
        "r": 509,
        "w": 0
    },
    {
        "c": 64,
        "d": 1757635200,
        "e": 843,
        "o": 519,
        "p": 1,
        "r": 510,
        "w": 0
    },
    {
        "c": 64,
        "d": 1757030400,
        "e": 842,
        "o": 515,
        "p": 1,
        "r": 510,
        "w": 0
    },
    {
        "c": 63,
        "d": 1756425600,
        "e": 842,
        "o": 512,
        "p": 1,
        "r": 511,
        "w": 0
    },
    {
        "c": 63,
        "d": 1755820800,
        "e": 841,
        "o": 510,
        "p": 1,
        "r": 512,
        "w": 0
    },
    {
        "c": 63,
        "d": 1755216000,
        "e": 841,
        "o": 505,
        "p": 1,
        "r": 512,
        "w": 0
    },
    {
        "c": 63,
        "d": 1754611200,
        "e": 840,
        "o": 503,
        "p": 1,
        "r": 513,
        "w": 0
    },
    {
        "c": 63,
        "d": 1754006400,
        "e": 839,
        "o": 503,
        "p": 1,
        "r": 513,
        "w": 0
    },
    {
        "c": 63,
        "d": 1753401600,
        "e": 839,
        "o": 495,
        "p": 1,
        "r": 514,
        "w": 0
    },
    {
        "c": 63,
        "d": 1752796800,
        "e": 838,
        "o": 491,
        "p": 1,
        "r": 514,
        "w": 0
    },
    {
        "c": 63,
        "d": 1752192000,
        "e": 838,
        "o": 490,
        "p": 1,
        "r": 515,
        "w": 0
    },
    {
        "c": 62,
        "d": 1751587200,
        "e": 837,
        "o": 486,
        "p": 1,
        "r": 516,
        "w": 0
    },
    {
        "c": 63,
        "d": 1750982400,
        "e": 836,
        "o": 485,
        "p": 1,
        "r": 516,
        "w": 0
    },
    {
        "c": 63,
        "d": 1750377600,
        "e": 836,
        "o": 483,
        "p": 1,
        "r": 517,
        "w": 0
    },
    {
        "c": 63,
        "d": 1749772800,
        "e": 835,
        "o": 485,
        "p": 1,
        "r": 517,
        "w": 0
    },
    {
        "c": 63,
        "d": 1749168000,
        "e": 835,
        "o": 483,
        "p": 1,
        "r": 518,
        "w": 0
    },
    {
        "c": 62,
        "d": 1748563200,
        "e": 834,
        "o": 478,
        "p": 1,
        "r": 519,
        "w": 0
    },
    {
        "c": 63,
        "d": 1747958400,
        "e": 834,
        "o": 481,
        "p": 1,
        "r": 519,
        "w": 0
    },
    {
        "c": 63,
        "d": 1747353600,
        "e": 833,
        "o": 475,
        "p": 1,
        "r": 520,
        "w": 0
    },
    {
        "c": 63,
        "d": 1746748800,
        "e": 832,
        "o": 475,
        "p": 1,
        "r": 520,
        "w": 0
    },
    {
        "c": 62,
        "d": 1746144000,
        "e": 832,
        "o": 470,
        "p": 1,
        "r": 521,
        "w": 0
    },
    {
        "c": 63,
        "d": 1745539200,
        "e": 831,
        "o": 470,
        "p": 1,
        "r": 522,
        "w": 0
    },
    {
        "c": 62,
        "d": 1744934400,
        "e": 831,
        "o": 466,
        "p": 1,
        "r": 522,
        "w": 0
    },
    {
        "c": 62,
        "d": 1744329600,
        "e": 830,
        "o": 466,
        "p": 1,
        "r": 523,
        "w": 0
    },
    {
        "c": 62,
        "d": 1743724800,
        "e": 829,
        "o": 465,
        "p": 1,
        "r": 523,
        "w": 0
    },
    {
        "c": 62,
        "d": 1743120000,
        "e": 829,
        "o": 464,
        "p": 1,
        "r": 524,
        "w": 0
    },
    {
        "c": 62,
        "d": 1742515200,
        "e": 828,
        "o": 464,
        "p": 1,
        "r": 524,
        "w": 0
    },
    {
        "c": 62,
        "d": 1741910400,
        "e": 828,
        "o": 463,
        "p": 1,
        "r": 525,
        "w": 0
    },
    {
        "c": 62,
        "d": 1741305600,
        "e": 827,
        "o": 463,
        "p": 1,
        "r": 526,
        "w": 0
    },
    {
        "c": 62,
        "d": 1740700800,
        "e": 826,
        "o": 462,
        "p": 1,
        "r": 526,
        "w": 0
    },
    {
        "c": 62,
        "d": 1740096000,
        "e": 826,
        "o": 460,
        "p": 1,
        "r": 527,
        "w": 0
    },
    {
        "c": 62,
        "d": 1739491200,
        "e": 825,
        "o": 455,
        "p": 1,
        "r": 527,
        "w": 0
    },
    {
        "c": 62,
        "d": 1738886400,
        "e": 825,
        "o": 450,
        "p": 1,
        "r": 528,
        "w": 0
    },
    {
        "c": 62,
        "d": 1738281600,
        "e": 824,
        "o": 446,
        "p": 1,
        "r": 529,
        "w": 0
    },
    {
        "c": 62,
        "d": 1737676800,
        "e": 823,
        "o": 444,
        "p": 1,
        "r": 529,
        "w": 0
    },
    {
        "c": 61,
        "d": 1737072000,
        "e": 823,
        "o": 441,
        "p": 1,
        "r": 530,
        "w": 0
    },
    {
        "c": 62,
        "d": 1736467200,
        "e": 822,
        "o": 441,
        "p": 1,
        "r": 530,
        "w": 0
    },
    {
        "c": 62,
        "d": 1735862400,
        "e": 822,
        "o": 438,
        "p": 1,
        "r": 531,
        "w": 0
    },
    {
        "c": 61,
        "d": 1735257600,
        "e": 821,
        "o": 436,
        "p": 1,
        "r": 532,
        "w": 0
    },
    {
        "c": 61,
        "d": 1734652800,
        "e": 821,
        "o": 433,
        "p": 1,
        "r": 532,
        "w": 0
    },
    {
        "c": 61,
        "d": 1734048000,
        "e": 820,
        "o": 432,
        "p": 1,
        "r": 533,
        "w": 0
    },
    {
        "c": 61,
        "d": 1733443200,
        "e": 819,
        "o": 430,
        "p": 1,
        "r": 533,
        "w": 0
    },
    {
        "c": 61,
        "d": 1732838400,
        "e": 819,
        "o": 425,
        "p": 1,
        "r": 534,
        "w": 0
    },
    {
        "c": 61,
        "d": 1732233600,
        "e": 818,
        "o": 423,
        "p": 1,
        "r": 535,
        "w": 0
    },
    {
        "c": 61,
        "d": 1731628800,
        "e": 818,
        "o": 422,
        "p": 1,
        "r": 535,
        "w": 0
    },
    {
        "c": 61,
        "d": 1731024000,
        "e": 817,
        "o": 422,
        "p": 1,
        "r": 536,
        "w": 0
    },
    {
        "c": 61,
        "d": 1730419200,
        "e": 816,
        "o": 423,
        "p": 1,
        "r": 536,
        "w": 0
    },
    {
        "c": 61,
        "d": 1729814400,
        "e": 816,
        "o": 421,
        "p": 1,
        "r": 537,
        "w": 0
    },
    {
        "c": 61,
        "d": 1729209600,
        "e": 815,
        "o": 420,
        "p": 1,
        "r": 538,
        "w": 0
    },
    {
        "c": 61,
        "d": 1728604800,
        "e": 815,
        "o": 418,
        "p": 1,
        "r": 538,
        "w": 0
    },
    {
        "c": 61,
        "d": 1728000000,
        "e": 814,
        "o": 416,
        "p": 1,
        "r": 539,
        "w": 0
    },
    {
        "c": 61,
        "d": 1727395200,
        "e": 813,
        "o": 417,
        "p": 1,
        "r": 539,
        "w": 0
    },
    {
        "c": 61,
        "d": 1726790400,
        "e": 813,
        "o": 415,
        "p": 1,
        "r": 540,
        "w": 0
    },
    {
        "c": 61,
        "d": 1726185600,
        "e": 812,
        "o": 414,
        "p": 1,
        "r": 541,
        "w": 0
    },
    {
        "c": 61,
        "d": 1725580800,
        "e": 812,
        "o": 414,
        "p": 1,
        "r": 541,
        "w": 0
    },
    {
        "c": 61,
        "d": 1724976000,
        "e": 811,
        "o": 412,
        "p": 1,
        "r": 542,
        "w": 0
    },
    {
        "c": 61,
        "d": 1724371200,
        "e": 810,
        "o": 413,
        "p": 1,
        "r": 542,
        "w": 0
    },
    {
        "c": 61,
        "d": 1723766400,
        "e": 810,
        "o": 412,
        "p": 1,
        "r": 543,
        "w": 0
    },
    {
        "c": 61,
        "d": 1723161600,
        "e": 809,
        "o": 412,
        "p": 1,
        "r": 544,
        "w": 0
    },
    {
        "c": 61,
        "d": 1722556800,
        "e": 809,
        "o": 411,
        "p": 1,
        "r": 544,
        "w": 0
    },
    {
        "c": 61,
        "d": 1721952000,
        "e": 808,
        "o": 408,
        "p": 1,
        "r": 545,
        "w": 0
    },
    {
        "c": 61,
        "d": 1721347200,
        "e": 807,
        "o": 408,
        "p": 1,
        "r": 545,
        "w": 0
    },
    {
        "c": 61,
        "d": 1720742400,
        "e": 807,
        "o": 406,
        "p": 1,
        "r": 546,
        "w": 0
    },
    {
        "c": 61,
        "d": 1720137600,
        "e": 806,
        "o": 405,
        "p": 1,
        "r": 547,
        "w": 0
    },
    {
        "c": 61,
        "d": 1719532800,
        "e": 805,
        "o": 403,
        "p": 1,
        "r": 547,
        "w": 0
    },
    {
        "c": 61,
        "d": 1718928000,
        "e": 805,
        "o": 402,
        "p": 1,
        "r": 548,
        "w": 0
    },
    {
        "c": 61,
        "d": 1718323200,
        "e": 804,
        "o": 403,
        "p": 1,
        "r": 548,
        "w": 0
    },
    {
        "c": 61,
        "d": 1717718400,
        "e": 804,
        "o": 401,
        "p": 1,
        "r": 549,
        "w": 0
    },
    {
        "c": 62,
        "d": 1717113600,
        "e": 803,
        "o": 400,
        "p": 1,
        "r": 550,
        "w": 0
    },
    {
        "c": 62,
        "d": 1716508800,
        "e": 802,
        "o": 400,
        "p": 1,
        "r": 550,
        "w": 0
    },
    {
        "c": 62,
        "d": 1715904000,
        "e": 802,
        "o": 399,
        "p": 1,
        "r": 551,
        "w": 0
    },
    {
        "c": 62,
        "d": 1715299200,
        "e": 801,
        "o": 399,
        "p": 1,
        "r": 551,
        "w": 0
    },
    {
        "c": 62,
        "d": 1714694400,
        "e": 801,
        "o": 398,
        "p": 1,
        "r": 552,
        "w": 0
    },
    {
        "c": 61,
        "d": 1714089600,
        "e": 800,
        "o": 393,
        "p": 1,
        "r": 553,
        "w": 0
    },
    {
        "c": 61,
        "d": 1713484800,
        "e": 799,
        "o": 391,
        "p": 1,
        "r": 553,
        "w": 0
    },
    {
        "c": 61,
        "d": 1712880000,
        "e": 799,
        "o": 389,
        "p": 1,
        "r": 554,
        "w": 0
    },
    {
        "c": 61,
        "d": 1712275200,
        "e": 798,
        "o": 385,
        "p": 1,
        "r": 555,
        "w": 0
    },
    {
        "c": 61,
        "d": 1711670400,
        "e": 798,
        "o": 384,
        "p": 1,
        "r": 555,
        "w": 0
    },
    {
        "c": 61,
        "d": 1711065600,
        "e": 797,
        "o": 380,
        "p": 1,
        "r": 556,
        "w": 0
    },
    {
        "c": 61,
        "d": 1710460800,
        "e": 796,
        "o": 379,
        "p": 1,
        "r": 556,
        "w": 0
    },
    {
        "c": 61,
        "d": 1709856000,
        "e": 796,
        "o": 378,
        "p": 1,
        "r": 557,
        "w": 0
    },
    {
        "c": 61,
        "d": 1709251200,
        "e": 795,
        "o": 375,
        "p": 1,
        "r": 558,
        "w": 0
    },
    {
        "c": 61,
        "d": 1708646400,
        "e": 794,
        "o": 375,
        "p": 1,
        "r": 558,
        "w": 0
    },
    {
        "c": 61,
        "d": 1708041600,
        "e": 794,
        "o": 375,
        "p": 1,
        "r": 559,
        "w": 0
    },
    {
        "c": 61,
        "d": 1707436800,
        "e": 793,
        "o": 375,
        "p": 1,
        "r": 559,
        "w": 0
    },
    {
        "c": 61,
        "d": 1706832000,
        "e": 793,
        "o": 375,
        "p": 1,
        "r": 560,
        "w": 0
    },
    {
        "c": 61,
        "d": 1706227200,
        "e": 792,
        "o": 373,
        "p": 1,
        "r": 561,
        "w": 0
    },
    {
        "c": 61,
        "d": 1705622400,
        "e": 791,
        "o": 373,
        "p": 1,
        "r": 561,
        "w": 0
    },
    {
        "c": 61,
        "d": 1705017600,
        "e": 791,
        "o": 373,
        "p": 1,
        "r": 562,
        "w": 0
    },
    {
        "c": 61,
        "d": 1704412800,
        "e": 790,
        "o": 372,
        "p": 1,
        "r": 563,
        "w": 0
    },
    {
        "c": 61,
        "d": 1703808000,
        "e": 790,
        "o": 372,
        "p": 1,
        "r": 563,
        "w": 0
    },
    {
        "c": 61,
        "d": 1703203200,
        "e": 789,
        "o": 372,
        "p": 1,
        "r": 564,
        "w": 0
    },
    {
        "c": 62,
        "d": 1702598400,
        "e": 788,
        "o": 372,
        "p": 1,
        "r": 564,
        "w": 0
    },
    {
        "c": 62,
        "d": 1701993600,
        "e": 788,
        "o": 372,
        "p": 1,
        "r": 565,
        "w": 0
    },
    {
        "c": 62,
        "d": 1701388800,
        "e": 787,
        "o": 372,
        "p": 1,
        "r": 566,
        "w": 0
    },
    {
        "c": 62,
        "d": 1700784000,
        "e": 786,
        "o": 373,
        "p": 1,
        "r": 566,
        "w": 0
    },
    {
        "c": 62,
        "d": 1700179200,
        "e": 786,
        "o": 371,
        "p": 1,
        "r": 567,
        "w": 0
    },
    {
        "c": 62,
        "d": 1699574400,
        "e": 785,
        "o": 370,
        "p": 1,
        "r": 567,
        "w": 0
    },
    {
        "c": 62,
        "d": 1698969600,
        "e": 785,
        "o": 370,
        "p": 1,
        "r": 568,
        "w": 0
    },
    {
        "c": 62,
        "d": 1698364800,
        "e": 784,
        "o": 369,
        "p": 1,
        "r": 569,
        "w": 0
    },
    {
        "c": 62,
        "d": 1697760000,
        "e": 783,
        "o": 370,
        "p": 1,
        "r": 569,
        "w": 0
    },
    {
        "c": 62,
        "d": 1697155200,
        "e": 783,
        "o": 365,
        "p": 1,
        "r": 570,
        "w": 0
    },
    {
        "c": 62,
        "d": 1696550400,
        "e": 782,
        "o": 362,
        "p": 1,
        "r": 571,
        "w": 0
    },
    {
        "c": 62,
        "d": 1695945600,
        "e": 781,
        "o": 358,
        "p": 1,
        "r": 571,
        "w": 0
    },
    {
        "c": 61,
        "d": 1695340800,
        "e": 781,
        "o": 356,
        "p": 1,
        "r": 572,
        "w": 0
    },
    {
        "c": 62,
        "d": 1694736000,
        "e": 780,
        "o": 355,
        "p": 1,
        "r": 572,
        "w": 0
    },
    {
        "c": 62,
        "d": 1694131200,
        "e": 780,
        "o": 353,
        "p": 1,
        "r": 573,
        "w": 0
    },
    {
        "c": 62,
        "d": 1693526400,
        "e": 779,
        "o": 353,
        "p": 1,
        "r": 574,
        "w": 0
    },
    {
        "c": 62,
        "d": 1692921600,
        "e": 778,
        "o": 351,
        "p": 1,
        "r": 574,
        "w": 0
    },
    {
        "c": 61,
        "d": 1692316800,
        "e": 778,
        "o": 349,
        "p": 1,
        "r": 575,
        "w": 0
    },
    {
        "c": 61,
        "d": 1691712000,
        "e": 777,
        "o": 348,
        "p": 1,
        "r": 576,
        "w": 0
    },
    {
        "c": 61,
        "d": 1691107200,
        "e": 776,
        "o": 345,
        "p": 1,
        "r": 576,
        "w": 0
    },
    {
        "c": 61,
        "d": 1690502400,
        "e": 776,
        "o": 345,
        "p": 1,
        "r": 577,
        "w": 0
    },
    {
        "c": 61,
        "d": 1689897600,
        "e": 775,
        "o": 343,
        "p": 1,
        "r": 578,
        "w": 0
    },
    {
        "c": 62,
        "d": 1689292800,
        "e": 775,
        "o": 342,
        "p": 1,
        "r": 578,
        "w": 0
    },
    {
        "c": 61,
        "d": 1688688000,
        "e": 774,
        "o": 339,
        "p": 1,
        "r": 579,
        "w": 0
    },
    {
        "c": 61,
        "d": 1688083200,
        "e": 773,
        "o": 336,
        "p": 1,
        "r": 579,
        "w": 0
    },
    {
        "c": 62,
        "d": 1687478400,
        "e": 773,
        "o": 336,
        "p": 1,
        "r": 580,
        "w": 0
    },
    {
        "c": 61,
        "d": 1686873600,
        "e": 772,
        "o": 331,
        "p": 1,
        "r": 581,
        "w": 0
    },
    {
        "c": 62,
        "d": 1686268800,
        "e": 771,
        "o": 329,
        "p": 1,
        "r": 581,
        "w": 0
    },
    {
        "c": 62,
        "d": 1685664000,
        "e": 771,
        "o": 327,
        "p": 1,
        "r": 582,
        "w": 0
    },
    {
        "c": 62,
        "d": 1685059200,
        "e": 770,
        "o": 325,
        "p": 1,
        "r": 583,
        "w": 0
    },
    {
        "c": 62,
        "d": 1684454400,
        "e": 769,
        "o": 325,
        "p": 1,
        "r": 583,
        "w": 0
    },
    {
        "c": 62,
        "d": 1683849600,
        "e": 769,
        "o": 325,
        "p": 1,
        "r": 584,
        "w": 0
    },
    {
        "c": 62,
        "d": 1683244800,
        "e": 768,
        "o": 323,
        "p": 1,
        "r": 584,
        "w": 0
    },
    {
        "c": 61,
        "d": 1682640000,
        "e": 768,
        "o": 318,
        "p": 1,
        "r": 585,
        "w": 0
    },
    {
        "c": 61,
        "d": 1682035200,
        "e": 767,
        "o": 315,
        "p": 1,
        "r": 586,
        "w": 0
    },
    {
        "c": 61,
        "d": 1681430400,
        "e": 766,
        "o": 312,
        "p": 1,
        "r": 586,
        "w": 0
    },
    {
        "c": 61,
        "d": 1680825600,
        "e": 766,
        "o": 312,
        "p": 1,
        "r": 587,
        "w": 0
    },
    {
        "c": 61,
        "d": 1680220800,
        "e": 765,
        "o": 309,
        "p": 1,
        "r": 588,
        "w": 0
    },
    {
        "c": 62,
        "d": 1679616000,
        "e": 764,
        "o": 307,
        "p": 1,
        "r": 588,
        "w": 0
    },
    {
        "c": 61,
        "d": 1679011200,
        "e": 764,
        "o": 300,
        "p": 1,
        "r": 589,
        "w": 0
    },
    {
        "c": 61,
        "d": 1678406400,
        "e": 763,
        "o": 299,
        "p": 1,
        "r": 590,
        "w": 0
    },
    {
        "c": 61,
        "d": 1677801600,
        "e": 762,
        "o": 296,
        "p": 1,
        "r": 590,
        "w": 0
    },
    {
        "c": 61,
        "d": 1677196800,
        "e": 762,
        "o": 292,
        "p": 1,
        "r": 591,
        "w": 0
    },
    {
        "c": 61,
        "d": 1676592000,
        "e": 761,
        "o": 290,
        "p": 1,
        "r": 592,
        "w": 0
    },
    {
        "c": 60,
        "d": 1675987200,
        "e": 761,
        "o": 287,
        "p": 1,
        "r": 592,
        "w": 0
    },
    {
        "c": 60,
        "d": 1675382400,
        "e": 760,
        "o": 280,
        "p": 1,
        "r": 593,
        "w": 0
    },
    {
        "c": 60,
        "d": 1674777600,
        "e": 759,
        "o": 278,
        "p": 1,
        "r": 593,
        "w": 0
    },
    {
        "c": 60,
        "d": 1674172800,
        "e": 759,
        "o": 277,
        "p": 1,
        "r": 594,
        "w": 0
    },
    {
        "c": 60,
        "d": 1673568000,
        "e": 758,
        "o": 276,
        "p": 1,
        "r": 595,
        "w": 0
    },
    {
        "c": 60,
        "d": 1672963200,
        "e": 757,
        "o": 276,
        "p": 1,
        "r": 595,
        "w": 0
    },
    {
        "c": 61,
        "d": 1672358400,
        "e": 757,
        "o": 276,
        "p": 1,
        "r": 596,
        "w": 0
    },
    {
        "c": 60,
        "d": 1671753600,
        "e": 756,
        "o": 274,
        "p": 1,
        "r": 597,
        "w": 0
    },
    {
        "c": 60,
        "d": 1671148800,
        "e": 755,
        "o": 274,
        "p": 1,
        "r": 597,
        "w": 0
    },
    {
        "c": 60,
        "d": 1670544000,
        "e": 755,
        "o": 274,
        "p": 1,
        "r": 598,
        "w": 0
    },
    {
        "c": 61,
        "d": 1669939200,
        "e": 754,
        "o": 273,
        "p": 1,
        "r": 599,
        "w": 0
    },
    {
        "c": 61,
        "d": 1669334400,
        "e": 753,
        "o": 273,
        "p": 1,
        "r": 599,
        "w": 0
    },
    {
        "c": 61,
        "d": 1668729600,
        "e": 753,
        "o": 272,
        "p": 1,
        "r": 600,
        "w": 0
    },
    {
        "c": 61,
        "d": 1668124800,
        "e": 752,
        "o": 272,
        "p": 1,
        "r": 601,
        "w": 0
    },
    {
        "c": 61,
        "d": 1667520000,
        "e": 751,
        "o": 270,
        "p": 1,
        "r": 601,
        "w": 0
    },
    {
        "c": 60,
        "d": 1666915200,
        "e": 751,
        "o": 267,
        "p": 1,
        "r": 602,
        "w": 0
    },
    {
        "c": 60,
        "d": 1666310400,
        "e": 750,
        "o": 263,
        "p": 1,
        "r": 603,
        "w": 0
    },
    {
        "c": 60,
        "d": 1665705600,
        "e": 750,
        "o": 263,
        "p": 1,
        "r": 603,
        "w": 0
    }
]