[
    {
        "c": 100,
        "d": 1785456000,
        "e": 981,
        "o": 915,
        "p": 1,
        "r": -63,
        "w": 0
    },
    {
        "c": 100,
        "d": 1784851200,
        "e": 981,
        "o": 916,
        "p": 1,
        "r": -62,
        "w": 0
    },
    {
        "c": 100,
        "d": 1784246400,
        "e": 980,
        "o": 916,
        "p": 1,
        "r": -62,
        "w": 0
    },
    {
        "c": 100,
        "d": 1783641600,
        "e": 980,
        "o": 916,
        "p": 1,
        "r": -61,
        "w": 0
    },
    {
        "c": 100,
        "d": 1783036800,
        "e": 979,
        "o": 916,
        "p": 1,
        "r": -61,
        "w": 0
    }
]