[
    {
        "i": 6646,
        "r": 1895,
        "e": 275,
        "p": 53,
        "w": 49
    },
    {
        "i": 6528,
        "r": 1841,
        "e": 243,
        "p": 65,
        "w": 57
    },
    {
        "i": 6680,
        "r": 1780,
        "e": 311,
        "p": 41,
        "w": 37
    },
    {
        "i": 6790,
        "r": 1760,
        "e": 224,
        "p": 81,
        "w": 57
    },
    {
        "i": 6586,
        "r": 1726,
        "e": 226,
        "p": 63,
        "w": 47
    },
    {
        "i": 6608,
        "r": 1721,
        "e": 308,
        "p": 34,
        "w": 32
    },
    {
        "i": 6026,
        "r": 1657,
        "e": 217,
        "p": 77,
        "w": 47
    },
    {
        "i": 6832,
        "r": 1639,
        "e": 297,
        "p": 25,
        "w": 19
    },
    {
        "i": 6504,
        "r": 1627,
        "e": 353,
        "p": 23,
        "w": 19
    },
    {
        "i": 6896,
        "r": 1617,
        "e": 336,
        "p": 19,
        "w": 15
    },
    {
        "i": 6748,
        "r": 1606,
        "e": 247,
        "p": 56,
        "w": 40
    },
    {
        "i": 4527,
        "r": 1595,
        "e": 242,
        "p": 68,
        "w": 44
    },
    {
        "i": 6938,
        "r": 1591,
        "e": 312,
        "p": 24,
        "w": 17
    },
    {
        "i": 6410,
        "r": 1588,
        "e": 311,
        "p": 40,
        "w": 31
    },
    {
        "i": 6793,
        "r": 1527,
        "e": 339,
        "p": 22,
        "w": 19
    },
    {
        "i": 2793,
        "r": 1488,
        "e": 238,
        "p": 65,
        "w": 40
    },
    {
        "i": 6757,
        "r": 1482,
        "e": 291,
        "p": 38,
        "w": 28
    },
    {
        "i": 5301,
        "r": 1460,
        "e": 429,
        "p": 21,
        "w": 18
    },
    {
        "i": 6318,
        "r": 1447,
        "e": 382,
        "p": 32,
        "w": 26
    },
    {
        "i": 6621,
        "r": 1425,
        "e": 252,
        "p": 44,
        "w": 25
    },
    {
        "i": -27,
        "r": 1423,
        "e": 368,
        "p": 16,
        "w": 13
    },
    {
        "i": 6812,
        "r": 1384,
        "e": 441,
        "p": 16,
        "w": 14
    },
    {
        "i": 6483,
        "r": 1381,
        "e": 453,
        "p": 14,
        "w": 12
    },
    {
        "i": 6430,
        "r": 1376,
        "e": 255,
        "p": 52,
        "w": 25
    },
    {
        "i": -19,
        "r": 1371,
        "e": 275,
        "p": 32,
        "w": 18
    },
    {
        "i": 6316,
        "r": 1356,
        "e": 277,
        "p": 60,
        "w": 34
    },
    {
        "i": 6822,
        "r": 1341,
        "e": 331,
        "p": 18,
        "w": 12
    },
    {
        "i": 3214,
        "r": 1339,
        "e": 310,
        "p": 44,
        "w": 20
    },
    {
        "i": 6625,
        "r": 1324,
        "e": 325,
        "p": 20,
        "w": 11
    },
    {
        "i": 4267,
        "r": 1323,
        "e": 488,
        "p": 14,
        "w": 12
    },
    {
        "i": -24,
        "r": 1306,
        "e": 343,
        "p": 18,
        "w": 11
    },
    {
        "i": -2,
        "r": 1304,
        "e": 250,
        "p": 67,
        "w": 32
    },
    {
        "i": 7472,
        "r": 1284,
        "e": 370,
        "p": 18,
        "w": 12
    },
    {
        "i": 6288,
        "r": 1271,
        "e": 260,
        "p": 63,
        "w": 30
    },
    {
        "i": 3952,
        "r": 1267,
        "e": 277,
        "p": 61,
        "w": 15
    },
    {
        "i": 4037,
        "r": 1249,
        "e": 256,
        "p": 71,
        "w": 26
    },
    {
        "i": 3812,
        "r": 1247,
        "e": 274,
        "p": 67,
        "w": 30
    },
    {
        "i": 6211,
        "r": 1242,
        "e": 262,
        "p": 48,
        "w": 19
    },
    {
        "i": 3958,
        "r": 1239,
        "e": 502,
        "p": 15,
        "w": 11
    },
    {
        "i": 6883,
        "r": 1239,
        "e": 320,
        "p": 18,
        "w": 8
    },
    {
        "i": 6265,
        "r": 1237,
        "e": 340,
        "p": 29,
        "w": 17
    },
    {
        "i": 6695,
        "r": 1223,
        "e": 479,
        "p": 12,
        "w": 9
    },
    {
        "i": -4,
        "r": 1221,
        "e": 449,
        "p": 18,
        "w": 11
    },
    {
        "i": 2580,
        "r": 1208,
        "e": 398,
        "p": 12,
        "w": 7
    },
    {
        "i": 6705,
        "r": 1207,
        "e": 347,
        "p": 17,
        "w": 9
    },
    {
        "i": -1,
        "r": 1200,
        "e": 488,
        "p": 12,
        "w": 8
    },
    {
        "i": 6859,
        "r": 1195,
        "e": 314,
        "p": 34,
        "w": 17
    },
    {
        "i": -6,
        "r": 1194,
        "e": 417,
        "p": 21,
        "w": 13
    },
    {
        "i": 12526,
        "r": 1183,
        "e": 611,
        "p": 6,
        "w": 4
    },
    {
        "i": -25,
        "r": 1169,
        "e": 370,
        "p": 16,
        "w": 8
    },
    {
        "i": -20,
        "r": 1139,
        "e": 378,
        "p": 20,
        "w": 6
    },
    {
        "i": 6723,
        "r": 1108,
        "e": 396,
        "p": 14,
        "w": 6
    },
    {
        "i": -22,
        "r": 1091,
        "e": 498,
        "p": 12,
        "w": 9
    },
    {
        "i": 6446,
        "r": 1086,
        "e": 312,
        "p": 32,
        "w": 17
    },
    {
        "i": 6665,
        "r": 1080,
        "e": 414,
        "p": 12,
        "w": 5
    },
    {
        "i": 6010,
        "r": 1060,
        "e": 488,
        "p": 14,
        "w": 7
    },
    {
        "i": 6856,
        "r": 1052,
        "e": 399,
        "p": 14,
        "w": 8
    },
    {
        "i": -5,
        "r": 1035,
        "e": 440,
        "p": 16,
        "w": 7
    },
    {
        "i": 6852,
        "r": 1031,
        "e": 361,
        "p": 18,
        "w": 8
    },
    {
        "i": 2321,
        "r": 1011,
        "e": 387,
        "p": 30,
        "w": 12
    },
    {
        "i": 4372,
        "r": 997,
        "e": 372,
        "p": 23,
        "w": 8
    },
    {
        "i": 235,
        "r": 989,
        "e": 453,
        "p": 18,
        "w": 6
    },
    {
        "i": 6766,
        "r": 987,
        "e": 760,
        "p": 2,
        "w": 2
    },
    {
        "i": 7234,
        "r": 987,
        "e": 760,
        "p": 2,
        "w": 2
    },
    {
        "i": 6771,
        "r": 987,
        "e": 760,
        "p": 2,
        "w": 2
    },
    {
        "i": 6941,
        "r": 987,
        "e": 760,
        "p": 2,
        "w": 2
    },
    {
        "i": 6415,
        "r": 981,
        "e": 425,
        "p": 20,
        "w": 7
    },
    {
        "i": 6336,
        "r": 980,
        "e": 439,
        "p": 12,
        "w": 6
    },
    {
        "i": -3,
        "r": 976,
        "e": 344,
        "p": 44,
        "w": 11
    },
    {
        "i": -9,
        "r": 963,
        "e": 283,
        "p": 52,
        "w": 9
    },
    {
        "i": 4155,
        "r": 960,
        "e": 567,
        "p": 8,
        "w": 3
    },
    {
        "i": 6390,
        "r": 951,
        "e": 500,
        "p": 10,
        "w": 4
    },
    {
        "i": 6056,
        "r": 931,
        "e": 486,
        "p": 14,
        "w": 5
    },
    {
        "i": 6751,
        "r": 930,
        "e": 303,
        "p": 37,
        "w": 11
    },
    {
        "i": -28,
        "r": 917,
        "e": 374,
        "p": 18,
        "w": 4
    },
    {
        "i": -11,
        "r": 913,
        "e": 685,
        "p": 4,
        "w": 2
    },
    {
        "i": 6740,
        "r": 898,
        "e": 614,
        "p": 5,
        "w": 3
    },
    {
        "i": -10,
        "r": 895,
        "e": 483,
        "p": 14,
        "w": 5
    },
    {
        "i": 6776,
        "r": 891,
        "e": 380,
        "p": 20,
        "w": 6
    },
    {
        "i": 6016,
        "r": 882,
        "e": 331,
        "p": 59,
        "w": 12
    },
    {
        "i": 3642,
        "r": 867,
        "e": 510,
        "p": 10,
        "w": 3
    },
    {
        "i": 6124,
        "r": 863,
        "e": 489,
        "p": 12,
        "w": 4
    },
    {
        "i": -26,
        "r": 853,
        "e": 522,
        "p": 6,
        "w": 3
    },
    {
        "i": -17,
        "r": 837,
        "e": 590,
        "p": 6,
        "w": 2
    },
    {
        "i": -33,
        "r": 813,
        "e": 615,
        "p": 4,
        "w": 2
    },
    {
        "i": 5661,
        "r": 791,
        "e": 871,
        "p": 1,
        "w": 1
    },
    {
        "i": -16,
        "r": 777,
        "e": 419,
        "p": 20,
        "w": 6
    },
    {
        "i": 7295,
        "r": 765,
        "e": 454,
        "p": 20,
        "w": 3
    },
    {
        "i": 6270,
        "r": 740,
        "e": 760,
        "p": 2,
        "w": 1
    },
    {
        "i": -34,
        "r": 740,
        "e": 760,
        "p": 2,
        "w": 1
    },
    {
        "i": 2333,
        "r": 711,
        "e": 402,
        "p": 34,
        "w": 6
    },
    {
        "i": 6881,
        "r": 700,
        "e": 397,
        "p": 20,
        "w": 2
    },
    {
        "i": -48,
        "r": 660,
        "e": 582,
        "p": 4,
        "w": 0
    },
    {
        "i": 6861,
        "r": 651,
        "e": 339,
        "p": 47,
        "w": 6
    },
    {
        "i": -18,
        "r": 593,
        "e": 407,
        "p": 18,
        "w": 3
    },
    {
        "i": 7229,
        "r": 585,
        "e": 537,
        "p": 16,
        "w": 3
    },
    {
        "i": 8152,
        "r": 572,
        "e": 429,
        "p": 10,
        "w": 0
    },
    {
        "i": 6231,
        "r": 571,
        "e": 966,
        "p": 2,
        "w": 2
    },
    {
        "i": -8,
        "r": 559,
        "e": 523,
        "p": 8,
        "w": 0
    },
    {
        "i": 6470,
        "r": 554,
        "e": 430,
        "p": 28,
        "w": 2
    },
    {
        "i": 4038,
        "r": 536,
        "e": 822,
        "p": 2,
        "w": 0
    },
    {
        "i": -23,
        "r": 512,
        "e": 438,
        "p": 16,
        "w": 0
    },
    {
        "i": -32,
        "r": 511,
        "e": 951,
        "p": 1,
        "w": 0
    },
    {
        "i": -14,
        "r": 506,
        "e": 613,
        "p": 6,
        "w": 0
    },
    {
        "i": -36,
        "r": 492,
        "e": 760,
        "p": 2,
        "w": 0
    },
    {
        "i": 7304,
        "r": 492,
        "e": 760,
        "p": 2,
        "w": 0
    },
    {
        "i": -37,
        "r": 492,
        "e": 760,
        "p": 2,
        "w": 0
    },
    {
        "i": -12,
        "r": 479,
        "e": 611,
        "p": 9,
        "w": 0
    },
    {
        "i": 6891,
        "r": 474,
        "e": 779,
        "p": 2,
        "w": 0
    },
    {
        "i": -13,
        "r": 470,
        "e": 566,
        "p": 10,
        "w": 0
    },
    {
        "i": 6922,
        "r": 467,
        "e": 871,
        "p": 1,
        "w": 0
    },
    {
        "i": 6880,
        "r": 465,
        "e": 458,
        "p": 11,
        "w": 1
    },
    {
        "i": -21,
        "r": 458,
        "e": 795,
        "p": 2,
        "w": 0
    },
    {
        "i": 3534,
        "r": 449,
        "e": 518,
        "p": 8,
        "w": 0
    },
    {
        "i": -15,
        "r": 441,
        "e": 811,
        "p": 2,
        "w": 0
    },
    {
        "i": -7,
        "r": 439,
        "e": 540,
        "p": 14,
        "w": 0
    },
    {
        "i": -30,
        "r": 430,
        "e": 516,
        "p": 6,
        "w": 0
    },
    {
        "i": -31,
        "r": 424,
        "e": 599,
        "p": 6,
        "w": 0
    },
    {
        "i": 6750,
        "r": 413,
        "e": 717,
        "p": 2,
        "w": 0
    },
    {
        "i": 6355,
        "r": 405,
        "e": 672,
        "p": 4,
        "w": 0
    },
    {
        "i": 2196,
        "r": 390,
        "e": 457,
        "p": 18,
        "w": 0
    },
    {
        "i": -29,
        "r": 353,
        "e": 473,
        "p": 14,
        "w": 0
    },
    {
        "i": 5512,
        "r": 345,
        "e": 775,
        "p": 4,
        "w": 0
    }
]