[
    {
        "e": 246,
        "i": 9599,
        "p": 129,
        "r": 1916,
        "w": 115
    },
    {
        "e": 298,
        "i": 10757,
        "p": 96,
        "r": 1836,
        "w": 84
    },
    {
        "e": 280,
        "i": 13705,
        "p": 239,
        "r": 1813,
        "w": 207
    },
    {
        "e": 288,
        "i": 9558,
        "p": 95,
        "r": 1812,
        "w": 74
    },
    {
        "e": 511,
        "i": 6646,
        "p": 61,
        "r": 1667,
        "w": 56
    },
    {
        "e": 249,
        "i": 10747,
        "p": 262,
        "r": 1641,
        "w": 201
    },
    {
        "e": 285,
        "i": 7223,
        "p": 178,
        "r": 1638,
        "w": 116
    },
    {
        "e": 345,
        "i": 6766,
        "p": 131,
        "r": 1636,
        "w": 100
    },
    {
        "e": 297,
        "i": 6680,
        "p": 179,
        "r": 1568,
        "w": 133
    },
    {
        "e": 198,
        "i": 6771,
        "p": 353,
        "r": 1561,
        "w": 231
    },
    {
        "e": 209,
        "i": 11705,
        "p": 223,
        "r": 1541,
        "w": 160
    },
    {
        "e": 225,
        "i": 12283,
        "p": 152,
        "r": 1536,
        "w": 109
    },
    {
        "e": 423,
        "i": 6790,
        "p": 147,
        "r": 1526,
        "w": 104
    },
    {
        "e": 458,
        "i": 6504,
        "p": 33,
        "r": 1491,
        "w": 26
    },
    {
        "e": 546,
        "i": 6608,
        "p": 34,
        "r": 1481,
        "w": 32
    },
    {
        "e": 201,
        "i": 9877,
        "p": 290,
        "r": 1480,
        "w": 187
    },
    {
        "e": 369,
        "i": 6748,
        "p": 168,
        "r": 1475,
        "w": 115
    },
    {
        "e": 207,
        "i": 7304,
        "p": 218,
        "r": 1470,
        "w": 93
    },
    {
        "e": 244,
        "i": 6723,
        "p": 284,
        "r": 1466,
        "w": 169
    },
    {
        "e": 305,
        "i": 13191,
        "p": 29,
        "r": 1455,
        "w": 22
    },
    {
        "e": 284,
        "i": 6430,
        "p": 134,
        "r": 1452,
        "w": 78
    },
    {
        "e": 232,
        "i": 7234,
        "p": 486,
        "r": 1437,
        "w": 263
    },
    {
        "e": 501,
        "i": 6832,
        "p": 39,
        "r": 1427,
        "w": 30
    },
    {
        "e": 271,
        "i": 6534,
        "p": 111,
        "r": 1427,
        "w": 66
    },
    {
        "e": 393,
        "i": 14216,
        "p": 15,
        "r": 1426,
        "w": 12
    },
    {
        "e": 190,
        "i": 15421,
        "p": 84,
        "r": 1420,
        "w": 64
    },
    {
        "e": 473,
        "i": 6586,
        "p": 83,
        "r": 1416,
        "w": 57
    },
    {
        "e": 538,
        "i": 9506,
        "p": 12,
        "r": 1413,
        "w": 11
    },
    {
        "e": 518,
        "i": 6410,
        "p": 41,
        "r": 1407,
        "w": 32
    },
    {
        "e": 222,
        "i": 7644,
        "p": 159,
        "r": 1407,
        "w": 90
    },
    {
        "e": 430,
        "i": 6695,
        "p": 72,
        "r": 1405,
        "w": 51
    },
    {
        "e": 182,
        "i": 11435,
        "p": 750,
        "r": 1382,
        "w": 391
    },
    {
        "e": 428,
        "i": 8790,
        "p": 30,
        "r": 1379,
        "w": 28
    },
    {
        "e": 303,
        "i": 10588,
        "p": 42,
        "r": 1379,
        "w": 25
    },
    {
        "e": 244,
        "i": 8494,
        "p": 176,
        "r": 1378,
        "w": 105
    },
    {
        "e": 222,
        "i": 3952,
        "p": 229,
        "r": 1371,
        "w": 92
    },
    {
        "e": 360,
        "i": 6528,
        "p": 88,
        "r": 1367,
        "w": 70
    },
    {
        "e": 175,
        "i": 11442,
        "p": 318,
        "r": 1356,
        "w": 188
    },
    {
        "e": 234,
        "i": 2982,
        "p": 112,
        "r": 1356,
        "w": 67
    },
    {
        "e": 247,
        "i": 10755,
        "p": 159,
        "r": 1348,
        "w": 74
    },
    {
        "e": 318,
        "i": 9473,
        "p": 46,
        "r": 1344,
        "w": 36
    },
    {
        "e": 199,
        "i": 11855,
        "p": 190,
        "r": 1329,
        "w": 69
    },
    {
        "e": 408,
        "i": 12526,
        "p": 19,
        "r": 1323,
        "w": 13
    },
    {
        "e": 194,
        "i": 9156,
        "p": 187,
        "r": 1322,
        "w": 94
    },
    {
        "e": 459,
        "i": 6026,
        "p": 91,
        "r": 1319,
        "w": 52
    },
    {
        "e": 194,
        "i": 16222,
        "p": 53,
        "r": 1319,
        "w": 35
    },
    {
        "e": 337,
        "i": 9453,
        "p": 27,
        "r": 1311,
        "w": 14
    },
    {
        "e": 194,
        "i": 6793,
        "p": 244,
        "r": 1299,
        "w": 131
    },
    {
        "e": 266,
        "i": 6865,
        "p": 128,
        "r": 1291,
        "w": 69
    },
    {
        "e": 558,
        "i": 6896,
        "p": 23,
        "r": 1273,
        "w": 17
    },
    {
        "e": 204,
        "i": 10862,
        "p": 278,
        "r": 1272,
        "w": 122
    },
    {
        "e": 622,
        "i": 5301,
        "p": 21,
        "r": 1267,
        "w": 18
    },
    {
        "e": 213,
        "i": 12444,
        "p": 63,
        "r": 1252,
        "w": 35
    },
    {
        "e": 241,
        "i": 4527,
        "p": 223,
        "r": 1247,
        "w": 106
    },
    {
        "e": 591,
        "i": 6318,
        "p": 32,
        "r": 1238,
        "w": 26
    },
    {
        "e": 311,
        "i": 7591,
        "p": 20,
        "r": 1228,
        "w": 15
    },
    {
        "e": 510,
        "i": 2793,
        "p": 65,
        "r": 1214,
        "w": 40
    },
    {
        "e": 202,
        "i": 12273,
        "p": 178,
        "r": 1210,
        "w": 80
    },
    {
        "e": 242,
        "i": 8869,
        "p": 86,
        "r": 1208,
        "w": 39
    },
    {
        "e": 293,
        "i": 13873,
        "p": 74,
        "r": 1205,
        "w": 26
    },
    {
        "e": 626,
        "i": 6812,
        "p": 18,
        "r": 1204,
        "w": 16
    },
    {
        "e": 255,
        "i": 12325,
        "p": 76,
        "r": 1201,
        "w": 44
    },
    {
        "e": 564,
        "i": -27,
        "p": 18,
        "r": 1198,
        "w": 14
    },
    {
        "e": 601,
        "i": 5661,
        "p": 11,
        "r": 1198,
        "w": 9
    },
    {
        "e": 374,
        "i": 9342,
        "p": 45,
        "r": 1197,
        "w": 20
    },
    {
        "e": 639,
        "i": 6483,
        "p": 14,
        "r": 1194,
        "w": 12
    },
    {
        "e": 650,
        "i": 16028,
        "p": 4,
        "r": 1192,
        "w": 4
    },
    {
        "e": 493,
        "i": 7696,
        "p": 22,
        "r": 1189,
        "w": 16
    },
    {
        "e": 207,
        "i": 7813,
        "p": 485,
        "r": 1189,
        "w": 161
    },
    {
        "e": 352,
        "i": 6938,
        "p": 42,
        "r": 1180,
        "w": 27
    },
    {
        "e": 292,
        "i": 8860,
        "p": 49,
        "r": 1175,
        "w": 24
    },
    {
        "e": 505,
        "i": 8769,
        "p": 18,
        "r": 1169,
        "w": 13
    },
    {
        "e": 435,
        "i": -41,
        "p": 41,
        "r": 1164,
        "w": 27
    },
    {
        "e": 218,
        "i": 13710,
        "p": 139,
        "r": 1164,
        "w": 57
    },
    {
        "e": 517,
        "i": 6621,
        "p": 44,
        "r": 1159,
        "w": 25
    },
    {
        "e": 265,
        "i": 6941,
        "p": 107,
        "r": 1152,
        "w": 58
    },
    {
        "e": 665,
        "i": 4267,
        "p": 14,
        "r": 1146,
        "w": 12
    },
    {
        "e": 439,
        "i": 6757,
        "p": 89,
        "r": 1136,
        "w": 54
    },
    {
        "e": 272,
        "i": 6856,
        "p": 129,
        "r": 1134,
        "w": 55
    },
    {
        "e": 583,
        "i": 16592,
        "p": 5,
        "r": 1133,
        "w": 4
    },
    {
        "e": 603,
        "i": 14508,
        "p": 4,
        "r": 1131,
        "w": 4
    },
    {
        "e": 245,
        "i": 5292,
        "p": 103,
        "r": 1130,
        "w": 43
    },
    {
        "e": 166,
        "i": 11099,
        "p": 248,
        "r": 1130,
        "w": 100
    },
    {
        "e": 535,
        "i": 6625,
        "p": 24,
        "r": 1129,
        "w": 14
    },
    {
        "e": 518,
        "i": 6705,
        "p": 29,
        "r": 1125,
        "w": 19
    },
    {
        "e": 244,
        "i": 12261,
        "p": 44,
        "r": 1125,
        "w": 24
    },
    {
        "e": 517,
        "i": 9283,
        "p": 9,
        "r": 1121,
        "w": 7
    },
    {
        "e": 226,
        "i": 11913,
        "p": 105,
        "r": 1119,
        "w": 48
    },
    {
        "e": 528,
        "i": -19,
        "p": 32,
        "r": 1116,
        "w": 18
    },
    {
        "e": 699,
        "i": 12760,
        "p": 3,
        "r": 1112,
        "w": 2
    },
    {
        "e": 547,
        "i": 3214,
        "p": 44,
        "r": 1102,
        "w": 20
    },
    {
        "e": 277,
        "i": 15899,
        "p": 22,
        "r": 1096,
        "w": 14
    },
    {
        "e": 706,
        "i": 15249,
        "p": 3,
        "r": 1094,
        "w": 3
    },
    {
        "e": 567,
        "i": -24,
        "p": 18,
        "r": 1083,
        "w": 11
    },
    {
        "e": 300,
        "i": 12892,
        "p": 62,
        "r": 1077,
        "w": 19
    },
    {
        "e": 438,
        "i": 14623,
        "p": 14,
        "r": 1077,
        "w": 10
    },
    {
        "e": 278,
        "i": 7299,
        "p": 147,
        "r": 1073,
        "w": 56
    },
    {
        "e": 583,
        "i": 7472,
        "p": 18,
        "r": 1070,
        "w": 12
    },
    {
        "e": 307,
        "i": 3817,
        "p": 70,
        "r": 1068,
        "w": 29
    },
    {
        "e": 675,
        "i": 3958,
        "p": 15,
        "r": 1066,
        "w": 11
    },
    {
        "e": 410,
        "i": 14726,
        "p": 10,
        "r": 1056,
        "w": 5
    },
    {
        "e": 391,
        "i": 10569,
        "p": 16,
        "r": 1054,
        "w": 10
    },
    {
        "e": 357,
        "i": 12160,
        "p": 17,
        "r": 1050,
        "w": 9
    },
    {
        "e": 448,
        "i": 16703,
        "p": 6,
        "r": 1050,
        "w": 4
    },
    {
        "e": 718,
        "i": 8031,
        "p": 3,
        "r": 1049,
        "w": 3
    },
    {
        "e": 285,
        "i": 6859,
        "p": 81,
        "r": 1048,
        "w": 40
    },
    {
        "e": 438,
        "i": 14631,
        "p": 14,
        "r": 1046,
        "w": 4
    },
    {
        "e": 585,
        "i": 12997,
        "p": 6,
        "r": 1042,
        "w": 4
    },
    {
        "e": 576,
        "i": 12877,
        "p": 10,
        "r": 1041,
        "w": 9
    },
    {
        "e": 516,
        "i": -2,
        "p": 67,
        "r": 1036,
        "w": 32
    },
    {
        "e": 637,
        "i": -4,
        "p": 18,
        "r": 1034,
        "w": 11
    },
    {
        "e": 593,
        "i": 14115,
        "p": 5,
        "r": 1034,
        "w": 3
    },
    {
        "e": 665,
        "i": -1,
        "p": 12,
        "r": 1023,
        "w": 8
    },
    {
        "e": 241,
        "i": 14596,
        "p": 35,
        "r": 1013,
        "w": 14
    },
    {
        "e": 504,
        "i": 6822,
        "p": 32,
        "r": 1009,
        "w": 14
    },
    {
        "e": 652,
        "i": 13730,
        "p": 4,
        "r": 1005,
        "w": 3
    },
    {
        "e": 615,
        "i": -6,
        "p": 21,
        "r": 997,
        "w": 13
    },
    {
        "e": 510,
        "i": 16004,
        "p": 8,
        "r": 996,
        "w": 5
    },
    {
        "e": 528,
        "i": 3812,
        "p": 67,
        "r": 993,
        "w": 30
    },
    {
        "e": 342,
        "i": 16401,
        "p": 17,
        "r": 990,
        "w": 8
    },
    {
        "e": 232,
        "i": 7617,
        "p": 71,
        "r": 987,
        "w": 20
    },
    {
        "e": 715,
        "i": 6487,
        "p": 2,
        "r": 986,
        "w": 2
    },
    {
        "e": 510,
        "i": 16003,
        "p": 8,
        "r": 985,
        "w": 3
    },
    {
        "e": 762,
        "i": 16630,
        "p": 2,
        "r": 985,
        "w": 2
    },
    {
        "e": 522,
        "i": 6211,
        "p": 48,
        "r": 980,
        "w": 19
    },
    {
        "e": 520,
        "i": 4037,
        "p": 69,
        "r": 974,
        "w": 25
    },
    {
        "e": 481,
        "i": 7212,
        "p": 15,
        "r": 974,
        "w": 9
    },
    {
        "e": 364,
        "i": 8894,
        "p": 48,
        "r": 973,
        "w": 23
    },
    {
        "e": 491,
        "i": 8152,
        "p": 26,
        "r": 970,
        "w": 11
    },
    {
        "e": 305,
        "i": 12790,
        "p": 23,
        "r": 968,
        "w": 7
    },
    {
        "e": 520,
        "i": 6316,
        "p": 61,
        "r": 965,
        "w": 34
    },
    {
        "e": 326,
        "i": 4175,
        "p": 28,
        "r": 965,
        "w": 11
    },
    {
        "e": 785,
        "i": 15567,
        "p": 2,
        "r": 965,
        "w": 2
    },
    {
        "e": 368,
        "i": 6974,
        "p": 48,
        "r": 962,
        "w": 23
    },
    {
        "e": 766,
        "i": 13174,
        "p": 2,
        "r": 957,
        "w": 2
    },
    {
        "e": 583,
        "i": -25,
        "p": 16,
        "r": 956,
        "w": 8
    },
    {
        "e": 505,
        "i": 6883,
        "p": 30,
        "r": 951,
        "w": 10
    },
    {
        "e": 486,
        "i": 13200,
        "p": 6,
        "r": 942,
        "w": 3
    },
    {
        "e": 881,
        "i": 11869,
        "p": 1,
        "r": 940,
        "w": 1
    },
    {
        "e": 378,
        "i": 2580,
        "p": 25,
        "r": 934,
        "w": 8
    },
    {
        "e": 358,
        "i": 11979,
        "p": 19,
        "r": 931,
        "w": 9
    },
    {
        "e": 366,
        "i": 12517,
        "p": 17,
        "r": 931,
        "w": 7
    },
    {
        "e": 589,
        "i": -20,
        "p": 20,
        "r": 928,
        "w": 6
    },
    {
        "e": 595,
        "i": -40,
        "p": 7,
        "r": 927,
        "w": 4
    },
    {
        "e": 445,
        "i": 6288,
        "p": 95,
        "r": 925,
        "w": 40
    },
    {
        "e": 333,
        "i": 14008,
        "p": 24,
        "r": 925,
        "w": 9
    },
    {
        "e": 226,
        "i": 7387,
        "p": 104,
        "r": 923,
        "w": 32
    },
    {
        "e": 593,
        "i": 6792,
        "p": 12,
        "r": 922,
        "w": 5
    },
    {
        "e": 672,
        "i": -22,
        "p": 12,
        "r": 917,
        "w": 9
    },
    {
        "e": 443,
        "i": -42,
        "p": 44,
        "r": 917,
        "w": 14
    },
    {
        "e": 687,
        "i": 16474,
        "p": 3,
        "r": 912,
        "w": 2
    },
    {
        "e": 375,
        "i": 6265,
        "p": 95,
        "r": 909,
        "w": 42
    },
    {
        "e": 647,
        "i": 11861,
        "p": 3,
        "r": 906,
        "w": 2
    },
    {
        "e": 520,
        "i": 6665,
        "p": 21,
        "r": 903,
        "w": 9
    },
    {
        "e": 665,
        "i": 6010,
        "p": 14,
        "r": 883,
        "w": 7
    },
    {
        "e": 677,
        "i": 16675,
        "p": 2,
        "r": 877,
        "w": 1
    },
    {
        "e": 446,
        "i": 7229,
        "p": 86,
        "r": 876,
        "w": 14
    },
    {
        "e": 310,
        "i": 12654,
        "p": 26,
        "r": 871,
        "w": 8
    },
    {
        "e": 277,
        "i": 6016,
        "p": 144,
        "r": 861,
        "w": 29
    },
    {
        "e": 347,
        "i": 8269,
        "p": 29,
        "r": 858,
        "w": 10
    },
    {
        "e": 495,
        "i": 14105,
        "p": 8,
        "r": 856,
        "w": 3
    },
    {
        "e": 549,
        "i": 6446,
        "p": 32,
        "r": 850,
        "w": 17
    },
    {
        "e": 262,
        "i": 7714,
        "p": 79,
        "r": 847,
        "w": 21
    },
    {
        "e": 630,
        "i": -5,
        "p": 16,
        "r": 845,
        "w": 7
    },
    {
        "e": 565,
        "i": 15130,
        "p": 4,
        "r": 845,
        "w": 2
    },
    {
        "e": 553,
        "i": 16089,
        "p": 4,
        "r": 840,
        "w": 2
    },
    {
        "e": 405,
        "i": 14725,
        "p": 11,
        "r": 837,
        "w": 4
    },
    {
        "e": 440,
        "i": 13039,
        "p": 12,
        "r": 829,
        "w": 4
    },
    {
        "e": 550,
        "i": 6852,
        "p": 22,
        "r": 828,
        "w": 10
    },
    {
        "e": 770,
        "i": 6270,
        "p": 4,
        "r": 827,
        "w": 3
    },
    {
        "e": 299,
        "i": 16066,
        "p": 27,
        "r": 824,
        "w": 7
    },
    {
        "e": 245,
        "i": 15428,
        "p": 50,
        "r": 819,
        "w": 8
    },
    {
        "e": 809,
        "i": 7313,
        "p": 5,
        "r": 809,
        "w": 5
    },
    {
        "e": 724,
        "i": 4155,
        "p": 8,
        "r": 802,
        "w": 3
    },
    {
        "e": 639,
        "i": 235,
        "p": 18,
        "r": 802,
        "w": 6
    },
    {
        "e": 334,
        "i": 7512,
        "p": 19,
        "r": 802,
        "w": 5
    },
    {
        "e": 546,
        "i": 13060,
        "p": 9,
        "r": 795,
        "w": 6
    },
    {
        "e": 289,
        "i": 6881,
        "p": 151,
        "r": 791,
        "w": 32
    },
    {
        "e": 871,
        "i": 16726,
        "p": 1,
        "r": 791,
        "w": 1
    },
    {
        "e": 871,
        "i": 16644,
        "p": 1,
        "r": 791,
        "w": 1
    },
    {
        "e": 284,
        "i": 6751,
        "p": 129,
        "r": 790,
        "w": 27
    },
    {
        "e": 629,
        "i": 6336,
        "p": 12,
        "r": 789,
        "w": 6
    },
    {
        "e": 812,
        "i": 15305,
        "p": 1,
        "r": 787,
        "w": 1
    },
    {
        "e": 619,
        "i": 6415,
        "p": 20,
        "r": 786,
        "w": 7
    },
    {
        "e": 877,
        "i": 16264,
        "p": 1,
        "r": 785,
        "w": 1
    },
    {
        "e": 585,
        "i": 4372,
        "p": 23,
        "r": 784,
        "w": 8
    },
    {
        "e": 822,
        "i": 14174,
        "p": 1,
        "r": 784,
        "w": 1
    },
    {
        "e": 879,
        "i": 16082,
        "p": 1,
        "r": 783,
        "w": 1
    },
    {
        "e": 820,
        "i": -11,
        "p": 4,
        "r": 778,
        "w": 2
    },
    {
        "e": 884,
        "i": 15679,
        "p": 1,
        "r": 778,
        "w": 1
    },
    {
        "e": 674,
        "i": 6390,
        "p": 10,
        "r": 777,
        "w": 4
    },
    {
        "e": 885,
        "i": 15639,
        "p": 1,
        "r": 777,
        "w": 1
    },
    {
        "e": 341,
        "i": 14974,
        "p": 17,
        "r": 776,
        "w": 4
    },
    {
        "e": 887,
        "i": 15445,
        "p": 1,
        "r": 775,
        "w": 1
    },
    {
        "e": 888,
        "i": 15302,
        "p": 1,
        "r": 774,
        "w": 1
    },
    {
        "e": 495,
        "i": 7787,
        "p": 7,
        "r": 772,
        "w": 2
    },
    {
        "e": 699,
        "i": 10220,
        "p": 2,
        "r": 769,
        "w": 1
    },
    {
        "e": 895,
        "i": 14146,
        "p": 1,
        "r": 768,
        "w": 1
    },
    {
        "e": 899,
        "i": 14627,
        "p": 1,
        "r": 764,
        "w": 1
    },
    {
        "e": 903,
        "i": 14296,
        "p": 1,
        "r": 759,
        "w": 1
    },
    {
        "e": 905,
        "i": 13169,
        "p": 1,
        "r": 757,
        "w": 1
    },
    {
        "e": 554,
        "i": 9438,
        "p": 4,
        "r": 755,
        "w": 0
    },
    {
        "e": 663,
        "i": 6056,
        "p": 14,
        "r": 754,
        "w": 5
    },
    {
        "e": 416,
        "i": 12964,
        "p": 12,
        "r": 754,
        "w": 4
    },
    {
        "e": 580,
        "i": 13763,
        "p": 5,
        "r": 754,
        "w": 2
    },
    {
        "e": 567,
        "i": -3,
        "p": 44,
        "r": 753,
        "w": 11
    },
    {
        "e": 592,
        "i": 13090,
        "p": 5,
        "r": 752,
        "w": 2
    },
    {
        "e": 762,
        "i": 6740,
        "p": 5,
        "r": 750,
        "w": 3
    },
    {
        "e": 640,
        "i": -35,
        "p": 10,
        "r": 745,
        "w": 3
    },
    {
        "e": 464,
        "i": 13101,
        "p": 8,
        "r": 741,
        "w": 4
    },
    {
        "e": 840,
        "i": 6664,
        "p": 2,
        "r": 741,
        "w": 2
    },
    {
        "e": 390,
        "i": 7344,
        "p": 25,
        "r": 740,
        "w": 7
    },
    {
        "e": 540,
        "i": -44,
        "p": 14,
        "r": 736,
        "w": 5
    },
    {
        "e": 703,
        "i": 6786,
        "p": 5,
        "r": 725,
        "w": 2
    },
    {
        "e": 640,
        "i": 7226,
        "p": 3,
        "r": 723,
        "w": 1
    },
    {
        "e": 603,
        "i": 9157,
        "p": 3,
        "r": 722,
        "w": 1
    },
    {
        "e": 509,
        "i": -45,
        "p": 14,
        "r": 721,
        "w": 2
    },
    {
        "e": 490,
        "i": -39,
        "p": 24,
        "r": 718,
        "w": 6
    },
    {
        "e": 661,
        "i": -10,
        "p": 14,
        "r": 717,
        "w": 5
    },
    {
        "e": 687,
        "i": 16314,
        "p": 3,
        "r": 713,
        "w": 1
    },
    {
        "e": 532,
        "i": -9,
        "p": 52,
        "r": 712,
        "w": 9
    },
    {
        "e": 240,
        "i": 13096,
        "p": 138,
        "r": 712,
        "w": 14
    },
    {
        "e": 292,
        "i": 6386,
        "p": 25,
        "r": 709,
        "w": 3
    },
    {
        "e": 586,
        "i": -28,
        "p": 18,
        "r": 705,
        "w": 4
    },
    {
        "e": 702,
        "i": 15057,
        "p": 3,
        "r": 701,
        "w": 1
    },
    {
        "e": 583,
        "i": 16594,
        "p": 5,
        "r": 700,
        "w": 1
    },
    {
        "e": 681,
        "i": 3642,
        "p": 10,
        "r": 696,
        "w": 3
    },
    {
        "e": 337,
        "i": 13258,
        "p": 48,
        "r": 693,
        "w": 5
    },
    {
        "e": 752,
        "i": 14394,
        "p": 2,
        "r": 693,
        "w": 1
    },
    {
        "e": 665,
        "i": 6124,
        "p": 12,
        "r": 687,
        "w": 4
    },
    {
        "e": 690,
        "i": -26,
        "p": 6,
        "r": 685,
        "w": 3
    },
    {
        "e": 743,
        "i": -17,
        "p": 6,
        "r": 684,
        "w": 2
    },
    {
        "e": 590,
        "i": 6776,
        "p": 20,
        "r": 682,
        "w": 6
    },
    {
        "e": 557,
        "i": 8620,
        "p": 4,
        "r": 679,
        "w": 1
    },
    {
        "e": 480,
        "i": -43,
        "p": 26,
        "r": 674,
        "w": 6
    },
    {
        "e": 762,
        "i": -33,
        "p": 4,
        "r": 665,
        "w": 2
    },
    {
        "e": 538,
        "i": 9800,
        "p": 5,
        "r": 665,
        "w": 2
    },
    {
        "e": 622,
        "i": 11782,
        "p": 3,
        "r": 661,
        "w": 1
    },
    {
        "e": 647,
        "i": 7427,
        "p": 2,
        "r": 655,
        "w": 0
    },
    {
        "e": 542,
        "i": 15293,
        "p": 5,
        "r": 654,
        "w": 1
    },
    {
        "e": 446,
        "i": 2321,
        "p": 48,
        "r": 652,
        "w": 13
    },
    {
        "e": 639,
        "i": -34,
        "p": 8,
        "r": 651,
        "w": 3
    },
    {
        "e": 579,
        "i": 12501,
        "p": 3,
        "r": 650,
        "w": 0
    },
    {
        "e": 426,
        "i": 11917,
        "p": 22,
        "r": 647,
        "w": 3
    },
    {
        "e": 665,
        "i": 13660,
        "p": 2,
        "r": 637,
        "w": 0
    },
    {
        "e": 555,
        "i": 14021,
        "p": 6,
        "r": 630,
        "w": 0
    },
    {
        "e": 609,
        "i": 12927,
        "p": 4,
        "r": 617,
        "w": 0
    },
    {
        "e": 489,
        "i": 13674,
        "p": 6,
        "r": 608,
        "w": 0
    },
    {
        "e": 678,
        "i": 13971,
        "p": 2,
        "r": 608,
        "w": 0
    },
    {
        "e": 728,
        "i": 13943,
        "p": 2,
        "r": 603,
        "w": 0
    },
    {
        "e": 502,
        "i": 13850,
        "p": 7,
        "r": 596,
        "w": 1
    },
    {
        "e": 772,
        "i": 15947,
        "p": 1,
        "r": 594,
        "w": 0
    },
    {
        "e": 762,
        "i": 15981,
        "p": 1,
        "r": 591,
        "w": 0
    },
    {
        "e": 478,
        "i": 13969,
        "p": 10,
        "r": 590,
        "w": 1
    },
    {
        "e": 542,
        "i": 11654,
        "p": 4,
        "r": 588,
        "w": 0
    },
    {
        "e": 759,
        "i": 6730,
        "p": 1,
        "r": 587,
        "w": 0
    },
    {
        "e": 640,
        "i": 14731,
        "p": 3,
        "r": 586,
        "w": 0
    },
    {
        "e": 792,
        "i": 15082,
        "p": 1,
        "r": 586,
        "w": 0
    },
    {
        "e": 436,
        "i": 13994,
        "p": 18,
        "r": 584,
        "w": 1
    },
    {
        "e": 800,
        "i": 13179,
        "p": 1,
        "r": 583,
        "w": 0
    },
    {
        "e": 759,
        "i": 13217,
        "p": 1,
        "r": 583,
        "w": 0
    },
    {
        "e": 518,
        "i": -47,
        "p": 12,
        "r": 581,
        "w": 2
    },
    {
        "e": 666,
        "i": 14285,
        "p": 2,
        "r": 581,
        "w": 0
    },
    {
        "e": 791,
        "i": 9865,
        "p": 1,
        "r": 581,
        "w": 0
    },
    {
        "e": 616,
        "i": -16,
        "p": 20,
        "r": 580,
        "w": 6
    },
    {
        "e": 640,
        "i": 7295,
        "p": 20,
        "r": 579,
        "w": 3
    },
    {
        "e": 790,
        "i": 14472,
        "p": 1,
        "r": 579,
        "w": 0
    },
    {
        "e": 790,
        "i": 5463,
        "p": 1,
        "r": 579,
        "w": 0
    },
    {
        "e": 806,
        "i": 13635,
        "p": 1,
        "r": 579,
        "w": 0
    },
    {
        "e": 704,
        "i": 14834,
        "p": 2,
        "r": 578,
        "w": 0
    },
    {
        "e": 517,
        "i": 7021,
        "p": 7,
        "r": 576,
        "w": 0
    },
    {
        "e": 774,
        "i": 8943,
        "p": 1,
        "r": 575,
        "w": 0
    },
    {
        "e": 623,
        "i": 3717,
        "p": 4,
        "r": 572,
        "w": 0
    },
    {
        "e": 533,
        "i": 10801,
        "p": 5,
        "r": 569,
        "w": 1
    },
    {
        "e": 844,
        "i": 7478,
        "p": 1,
        "r": 567,
        "w": 0
    },
    {
        "e": 781,
        "i": 15423,
        "p": 1,
        "r": 566,
        "w": 0
    },
    {
        "e": 801,
        "i": -56,
        "p": 2,
        "r": 561,
        "w": 0
    },
    {
        "e": 798,
        "i": 13884,
        "p": 1,
        "r": 558,
        "w": 0
    },
    {
        "e": 653,
        "i": 7568,
        "p": 3,
        "r": 557,
        "w": 0
    },
    {
        "e": 661,
        "i": 8255,
        "p": 2,
        "r": 554,
        "w": 0
    },
    {
        "e": 554,
        "i": 9465,
        "p": 10,
        "r": 552,
        "w": 0
    },
    {
        "e": 834,
        "i": 13708,
        "p": 1,
        "r": 552,
        "w": 0
    },
    {
        "e": 708,
        "i": 13559,
        "p": 2,
        "r": 546,
        "w": 0
    },
    {
        "e": 767,
        "i": 7653,
        "p": 1,
        "r": 546,
        "w": 0
    },
    {
        "e": 874,
        "i": 13378,
        "p": 1,
        "r": 543,
        "w": 0
    },
    {
        "e": 874,
        "i": 14560,
        "p": 1,
        "r": 543,
        "w": 0
    },
    {
        "e": 573,
        "i": 10262,
        "p": 4,
        "r": 542,
        "w": 1
    },
    {
        "e": 438,
        "i": 14229,
        "p": 12,
        "r": 541,
        "w": 1
    },
    {
        "e": 881,
        "i": 14453,
        "p": 1,
        "r": 538,
        "w": 0
    },
    {
        "e": 884,
        "i": 15643,
        "p": 1,
        "r": 536,
        "w": 0
    },
    {
        "e": 885,
        "i": 16434,
        "p": 1,
        "r": 536,
        "w": 0
    },
    {
        "e": 776,
        "i": 14600,
        "p": 1,
        "r": 534,
        "w": 0
    },
    {
        "e": 765,
        "i": 16080,
        "p": 1,
        "r": 529,
        "w": 0
    },
    {
        "e": 529,
        "i": 14467,
        "p": 6,
        "r": 524,
        "w": 0
    },
    {
        "e": 472,
        "i": 13872,
        "p": 12,
        "r": 521,
        "w": 0
    },
    {
        "e": 779,
        "i": 12399,
        "p": 1,
        "r": 517,
        "w": 0
    },
    {
        "e": 647,
        "i": 14473,
        "p": 4,
        "r": 514,
        "w": 1
    },
    {
        "e": 688,
        "i": 16256,
        "p": 3,
        "r": 512,
        "w": 0
    },
    {
        "e": 431,
        "i": 9249,
        "p": 16,
        "r": 511,
        "w": 1
    },
    {
        "e": 604,
        "i": 2333,
        "p": 34,
        "r": 509,
        "w": 6
    },
    {
        "e": 1013,
        "i": 9159,
        "p": 1,
        "r": 509,
        "w": 1
    },
    {
        "e": 1013,
        "i": 13750,
        "p": 1,
        "r": 509,
        "w": 1
    },
    {
        "e": 778,
        "i": 7571,
        "p": 1,
        "r": 508,
        "w": 0
    },
    {
        "e": 875,
        "i": 15663,
        "p": 1,
        "r": 508,
        "w": 0
    },
    {
        "e": 695,
        "i": 16029,
        "p": 3,
        "r": 506,
        "w": 0
    },
    {
        "e": 556,
        "i": 6251,
        "p": 5,
        "r": 503,
        "w": 0
    },
    {
        "e": 706,
        "i": 15248,
        "p": 3,
        "r": 495,
        "w": 0
    },
    {
        "e": 650,
        "i": 9989,
        "p": 4,
        "r": 494,
        "w": 0
    },
    {
        "e": 495,
        "i": 13077,
        "p": 8,
        "r": 492,
        "w": 0
    },
    {
        "e": 762,
        "i": 16631,
        "p": 2,
        "r": 491,
        "w": 0
    },
    {
        "e": 597,
        "i": 7954,
        "p": 3,
        "r": 490,
        "w": 0
    },
    {
        "e": 1050,
        "i": 6231,
        "p": 2,
        "r": 488,
        "w": 2
    },
    {
        "e": 790,
        "i": 11362,
        "p": 1,
        "r": 483,
        "w": 0
    },
    {
        "e": 737,
        "i": 12163,
        "p": 2,
        "r": 477,
        "w": 0
    },
    {
        "e": 726,
        "i": 13962,
        "p": 3,
        "r": 475,
        "w": 0
    },
    {
        "e": 472,
        "i": 7514,
        "p": 5,
        "r": 474,
        "w": 0
    },
    {
        "e": 871,
        "i": 16744,
        "p": 1,
        "r": 467,
        "w": 0
    },
    {
        "e": 871,
        "i": 16643,
        "p": 1,
        "r": 467,
        "w": 0
    },
    {
        "e": 799,
        "i": 14232,
        "p": 1,
        "r": 464,
        "w": 0
    },
    {
        "e": 514,
        "i": 7687,
        "p": 26,
        "r": 461,
        "w": 0
    },
    {
        "e": 877,
        "i": 16266,
        "p": 1,
        "r": 461,
        "w": 0
    },
    {
        "e": 796,
        "i": 14458,
        "p": 1,
        "r": 460,
        "w": 0
    },
    {
        "e": 879,
        "i": 16083,
        "p": 1,
        "r": 458,
        "w": 0
    },
    {
        "e": 640,
        "i": -48,
        "p": 7,
        "r": 457,
        "w": 0
    },
    {
        "e": 735,
        "i": 8419,
        "p": 2,
        "r": 456,
        "w": 0
    },
    {
        "e": 739,
        "i": 13704,
        "p": 3,
        "r": 454,
        "w": 0
    },
    {
        "e": 799,
        "i": 14070,
        "p": 2,
        "r": 454,
        "w": 0
    },
    {
        "e": 885,
        "i": 15652,
        "p": 1,
        "r": 453,
        "w": 0
    },
    {
        "e": 884,
        "i": 15678,
        "p": 1,
        "r": 453,
        "w": 0
    },
    {
        "e": 709,
        "i": 15047,
        "p": 2,
        "r": 452,
        "w": 0
    },
    {
        "e": 886,
        "i": 15568,
        "p": 1,
        "r": 452,
        "w": 0
    },
    {
        "e": 887,
        "i": 13512,
        "p": 1,
        "r": 451,
        "w": 0
    },
    {
        "e": 888,
        "i": 15315,
        "p": 1,
        "r": 450,
        "w": 0
    },
    {
        "e": 796,
        "i": 6855,
        "p": 1,
        "r": 449,
        "w": 0
    },
    {
        "e": 788,
        "i": 13822,
        "p": 2,
        "r": 448,
        "w": 0
    },
    {
        "e": 647,
        "i": 6922,
        "p": 7,
        "r": 447,
        "w": 0
    },
    {
        "e": 373,
        "i": 6861,
        "p": 65,
        "r": 446,
        "w": 6
    },
    {
        "e": 812,
        "i": 15021,
        "p": 1,
        "r": 445,
        "w": 0
    },
    {
        "e": 895,
        "i": 14149,
        "p": 1,
        "r": 443,
        "w": 0
    },
    {
        "e": 718,
        "i": 7498,
        "p": 2,
        "r": 441,
        "w": 0
    },
    {
        "e": 899,
        "i": 14626,
        "p": 1,
        "r": 439,
        "w": 0
    },
    {
        "e": 900,
        "i": 14490,
        "p": 1,
        "r": 437,
        "w": 0
    },
    {
        "e": 903,
        "i": 14297,
        "p": 1,
        "r": 435,
        "w": 0
    },
    {
        "e": 567,
        "i": 2900,
        "p": 18,
        "r": 434,
        "w": 0
    },
    {
        "e": 905,
        "i": 14099,
        "p": 1,
        "r": 433,
        "w": 0
    },
    {
        "e": 718,
        "i": 8797,
        "p": 12,
        "r": 431,
        "w": 2
    },
    {
        "e": 908,
        "i": 10428,
        "p": 1,
        "r": 430,
        "w": 0
    },
    {
        "e": 448,
        "i": 9965,
        "p": 32,
        "r": 422,
        "w": 3
    },
    {
        "e": 937,
        "i": 4038,
        "p": 2,
        "r": 421,
        "w": 0
    },
    {
        "e": 1050,
        "i": -32,
        "p": 1,
        "r": 411,
        "w": 0
    },
    {
        "e": 816,
        "i": 14601,
        "p": 1,
        "r": 402,
        "w": 0
    },
    {
        "e": 827,
        "i": 12090,
        "p": 1,
        "r": 400,
        "w": 0
    },
    {
        "e": 827,
        "i": 11584,
        "p": 1,
        "r": 400,
        "w": 0
    },
    {
        "e": 857,
        "i": -46,
        "p": 2,
        "r": 396,
        "w": 0
    },
    {
        "e": 824,
        "i": 10237,
        "p": 1,
        "r": 396,
        "w": 0
    },
    {
        "e": 812,
        "i": 12323,
        "p": 1,
        "r": 396,
        "w": 0
    },
    {
        "e": 540,
        "i": 13679,
        "p": 7,
        "r": 396,
        "w": 0
    },
    {
        "e": 608,
        "i": -18,
        "p": 18,
        "r": 393,
        "w": 3
    },
    {
        "e": 619,
        "i": 10751,
        "p": 4,
        "r": 393,
        "w": 0
    },
    {
        "e": 690,
        "i": -8,
        "p": 8,
        "r": 392,
        "w": 0
    },
    {
        "e": 686,
        "i": 11729,
        "p": 2,
        "r": 388,
        "w": 0
    },
    {
        "e": 770,
        "i": -36,
        "p": 4,
        "r": 386,
        "w": 0
    },
    {
        "e": 821,
        "i": -37,
        "p": 4,
        "r": 386,
        "w": 0
    },
    {
        "e": 738,
        "i": 16737,
        "p": 2,
        "r": 385,
        "w": 0
    },
    {
        "e": 451,
        "i": 6891,
        "p": 17,
        "r": 384,
        "w": 0
    },
    {
        "e": 812,
        "i": 15361,
        "p": 1,
        "r": 384,
        "w": 0
    },
    {
        "e": 821,
        "i": 10286,
        "p": 1,
        "r": 370,
        "w": 0
    },
    {
        "e": 699,
        "i": 13734,
        "p": 2,
        "r": 369,
        "w": 0
    },
    {
        "e": 831,
        "i": 7404,
        "p": 1,
        "r": 366,
        "w": 0
    },
    {
        "e": 821,
        "i": 15120,
        "p": 1,
        "r": 366,
        "w": 0
    },
    {
        "e": 623,
        "i": 6470,
        "p": 28,
        "r": 361,
        "w": 2
    },
    {
        "e": 761,
        "i": -14,
        "p": 6,
        "r": 358,
        "w": 0
    },
    {
        "e": 673,
        "i": -38,
        "p": 4,
        "r": 352,
        "w": 0
    },
    {
        "e": 829,
        "i": 15316,
        "p": 1,
        "r": 343,
        "w": 0
    },
    {
        "e": 829,
        "i": 13753,
        "p": 1,
        "r": 343,
        "w": 0
    },
    {
        "e": 873,
        "i": 13987,
        "p": 1,
        "r": 343,
        "w": 0
    },
    {
        "e": 914,
        "i": -21,
        "p": 2,
        "r": 339,
        "w": 0
    },
    {
        "e": 759,
        "i": -12,
        "p": 9,
        "r": 330,
        "w": 0
    },
    {
        "e": 867,
        "i": 9764,
        "p": 1,
        "r": 326,
        "w": 0
    },
    {
        "e": 928,
        "i": -15,
        "p": 2,
        "r": 325,
        "w": 0
    },
    {
        "e": 628,
        "i": -23,
        "p": 16,
        "r": 321,
        "w": 0
    },
    {
        "e": 724,
        "i": -13,
        "p": 10,
        "r": 312,
        "w": 0
    },
    {
        "e": 844,
        "i": 16448,
        "p": 1,
        "r": 305,
        "w": 0
    },
    {
        "e": 764,
        "i": 14276,
        "p": 2,
        "r": 291,
        "w": 0
    },
    {
        "e": 534,
        "i": 14579,
        "p": 8,
        "r": 288,
        "w": 0
    },
    {
        "e": 847,
        "i": 6750,
        "p": 2,
        "r": 283,
        "w": 0
    },
    {
        "e": 643,
        "i": 6880,
        "p": 11,
        "r": 280,
        "w": 1
    },
    {
        "e": 687,
        "i": 3534,
        "p": 8,
        "r": 280,
        "w": 0
    },
    {
        "e": 703,
        "i": -7,
        "p": 14,
        "r": 275,
        "w": 0
    },
    {
        "e": 750,
        "i": -31,
        "p": 6,
        "r": 274,
        "w": 0
    },
    {
        "e": 810,
        "i": 6355,
        "p": 4,
        "r": 268,
        "w": 0
    },
    {
        "e": 878,
        "i": 15210,
        "p": 1,
        "r": 266,
        "w": 0
    },
    {
        "e": 685,
        "i": -30,
        "p": 6,
        "r": 261,
        "w": 0
    },
    {
        "e": 897,
        "i": 5512,
        "p": 4,
        "r": 223,
        "w": 0
    },
    {
        "e": 641,
        "i": 2196,
        "p": 18,
        "r": 205,
        "w": 0
    },
    {
        "e": 908,
        "i": 14665,
        "p": 1,
        "r": 173,
        "w": 0
    },
    {
        "e": 653,
        "i": -29,
        "p": 14,
        "r": 172,
        "w": 0
    },
    {
        "e": 913,
        "i": 14769,
        "p": 1,
        "r": 165,
        "w": 0
    },
    {
        "e": 933,
        "i": 13518,
        "p": 1,
        "r": 106,
        "w": 0
    },
    {
        "e": 937,
        "i": 16601,
        "p": 1,
        "r": 102,
        "w": 0
    },
    {
        "e": 937,
        "i": 16647,
        "p": 1,
        "r": 102,
        "w": 0
    },
    {
        "e": 952,
        "i": 14578,
        "p": 1,
        "r": 53,
        "w": 0
    },
    {
        "e": 968,
        "i": 14938,
        "p": 1,
        "r": 48,
        "w": 0
    },
    {
        "e": 879,
        "i": 15155,
        "p": 3,
        "r": -9,
        "w": 0
    },
    {
        "e": 1016,
        "i": 10501,
        "p": 1,
        "r": -108,
        "w": 0
    },
    {
        "e": 896,
        "i": 12957,
        "p": 3,
        "r": -247,
        "w": 1
    }
]